{
  "filename": "image1.png",
  "detections": [
    {
      "cx": 85,
      "cy": 349,
      "size_px": 31,
      "angle_deg": 29,
      "color": "red"
    },
    {
      "cx": 98,
      "cy": 239,
      "size_px": 48,
      "angle_deg": 30,
      "color": "red"
    },
    {
      "cx": 139,
      "cy": 130,
      "size_px": 82,
      "angle_deg": 60,
      "color": "red"
    },
    {
      "cx": 324,
      "cy": 63,
      "size_px": 40,
      "angle_deg": 90,
      "color": "red"
    },
    {
      "cx": 476,
      "cy": 58,
      "size_px": 61,
      "angle_deg": 60,
      "color": "green"
    }
  ],
  "color_counts": {
    "red": 4,
    "green": 1,
    "blue": 0,
    "yellow": 0
  }
}